AUTHORS
LICENSE
MANIFEST.in
README.md
TrezorCrypto.c
TrezorCrypto.pyx
address.c
address.h
base32.h
base58.c
base58.h
bignum.c
bignum.h
bip32.c
bip32.h
bip39.h
bip39_english.h
blake256.c
blake256.h
blake2_common.h
blake2b.c
blake2b.h
blake2s.h
c.pxd
cash_addr.h
chacha_drbg.h
check_mem.h
curves.c
curves.h
ecdsa.c
ecdsa.h
groestl.c
groestl.h
groestl_internal.h
hasher.c
hasher.h
hmac.c
hmac.h
hmac_drbg.c
hmac_drbg.h
memzero.c
memzero.h
nem.h
nist256p1.c
nist256p1.h
nist256p1.table
options.h
pbkdf2.h
pyproject.toml
rand.c
rand.h
rc4.h
rfc6979.c
rfc6979.h
ripemd160.c
ripemd160.h
script.h
secp256k1.c
secp256k1.h
secp256k1.table
segwit_addr.h
setup.py
sha2.c
sha2.h
sha3.c
sha3.h
shamir.h
slip39.h
slip39_wordlist.h
TrezorCryptoTestRc.egg-info/PKG-INFO
TrezorCryptoTestRc.egg-info/SOURCES.txt
TrezorCryptoTestRc.egg-info/dependency_links.txt
TrezorCryptoTestRc.egg-info/top_level.txt
aes/aes.h
aes/aesopt.h
aes/aestab.h
aes/aestst.h
chacha20poly1305/chacha20poly1305.h
chacha20poly1305/ecrypt-config.h
chacha20poly1305/ecrypt-machine.h
chacha20poly1305/ecrypt-portable.h
chacha20poly1305/ecrypt-sync.h
chacha20poly1305/ecrypt-types.h
chacha20poly1305/poly1305-donna-32.h
chacha20poly1305/poly1305-donna.h
chacha20poly1305/rfc7539.h
ed25519-donna/curve25519-donna-32bit.c
ed25519-donna/curve25519-donna-32bit.h
ed25519-donna/curve25519-donna-helpers.c
ed25519-donna/curve25519-donna-helpers.h
ed25519-donna/curve25519-donna-scalarmult-base.c
ed25519-donna/curve25519-donna-scalarmult-base.h
ed25519-donna/ed25519-donna-32bit-tables.c
ed25519-donna/ed25519-donna-32bit-tables.h
ed25519-donna/ed25519-donna-basepoint-table.c
ed25519-donna/ed25519-donna-basepoint-table.h
ed25519-donna/ed25519-donna-impl-base.c
ed25519-donna/ed25519-donna-impl-base.h
ed25519-donna/ed25519-donna-portable.h
ed25519-donna/ed25519-donna.h
ed25519-donna/ed25519-hash-custom-keccak.h
ed25519-donna/ed25519-hash-custom-sha3.h
ed25519-donna/ed25519-hash-custom.h
ed25519-donna/ed25519-keccak.c
ed25519-donna/ed25519-keccak.h
ed25519-donna/ed25519-sha3.c
ed25519-donna/ed25519-sha3.h
ed25519-donna/ed25519.c
ed25519-donna/ed25519.h
ed25519-donna/modm-donna-32bit.c
